SQLConn/SQLConn.py
SQLConn/__init__.py
SQLConn-0.0.16.dist-info/METADATA
SQLConn-0.0.16.dist-info/WHEEL
SQLConn-0.0.16.dist-info/top_level.txt
SQLConn-0.0.16.dist-info/RECORD
