Metadata-Version: 2.1
Name: SQLConn
Version: 0.0.16
Summary: This package facilitates easy SQL database integration.
Home-page: https://github.com/janyoungjin/SQLConn
Author: janyoungjin
Keywords: mysql,postgresql,sqlite,mssql,sql
Classifier: Programming Language :: Python :: 3
Classifier: License :: OSI Approved :: MIT License
Classifier: Operating System :: OS Independent
Requires-Python: >=3.6
Requires-Dist: pandas
Requires-Dist: sqlalchemy
Requires-Dist: pymysql
Requires-Dist: pymssql
Requires-Dist: psycopg2-binary
